cleanse-0.1.1.dist-info/METADATA
cleanse-0.1.1.dist-info/WHEEL
cleanse-0.1.1.dist-info/entry_points.txt
cleanse/__init__.py
cleanse/cli.py
cleanse/core.py
cleanse/utils.py
cleanse-0.1.1.dist-info/RECORD
